[
  {
    "full_name": "olegos2/mobox",
    "stargazers_count": 3524,
    "open_issues_count": 389,
    "forks_count": 174
  },
  {
    "full_name": "shrimqy/Sefirah",
    "stargazers_count": 1140,
    "open_issues_count": 69,
    "forks_count": 20
  },
  {
    "full_name": "TechnitiumSoftware/DnsServer",
    "stargazers_count": 5754,
    "open_issues_count": 125,
    "forks_count": 499
  },
  {
    "full_name": "system-linux/FazJammer",
    "stargazers_count": 1053,
    "open_issues_count": 5,
    "forks_count": 76
  },
  {
    "full_name": "cenonym/trmt",
    "stargazers_count": 75,
    "open_issues_count": 0,
    "forks_count": 4
  },
  {
    "full_name": "super-linter/super-linter",
    "stargazers_count": 9946,
    "open_issues_count": 33,
    "forks_count": 1013
  },
  {
    "full_name": "HOAIAN2/Instagram-Downloader",
    "stargazers_count": 232,
    "open_issues_count": 1,
    "forks_count": 33
  },
  {
    "full_name": "Discord-Client-Encyclopedia-Management/Discord3rdparties",
    "stargazers_count": 1833,
    "open_issues_count": 4,
    "forks_count": 76
  },
  {
    "full_name": "programmer2514/BetterDiscord-CollapsibleUI",
    "stargazers_count": 86,
    "open_issues_count": 2,
    "forks_count": 9
  },
  {
    "full_name": "Yahiamice/yahimod-balatro",
    "stargazers_count": 91,
    "open_issues_count": 32,
    "forks_count": 12
  },
  {
    "full_name": "Alaa-MK/dotfiles",
    "stargazers_count": 28,
    "open_issues_count": 0,
    "forks_count": 0
  },
  {
    "full_name": "alangrainger/obsidian-lazy-plugins",
    "stargazers_count": 366,
    "open_issues_count": 4,
    "forks_count": 2
  },
  {
    "full_name": "mgmeyers/obsidian-contextual-typography",
    "stargazers_count": 179,
    "open_issues_count": 8,
    "forks_count": 9
  },
  {
    "full_name": "Hillobar/Rope",
    "stargazers_count": 5069,
    "open_issues_count": 25,
    "forks_count": 872
  },
  {
    "full_name": "deckerst/aves",
    "stargazers_count": 3666,
    "open_issues_count": 129,
    "forks_count": 129
  },
  {
    "full_name": "dinerojs/dinero.js",
    "stargazers_count": 6473,
    "open_issues_count": 41,
    "forks_count": 193
  },
  {
    "full_name": "backstage/backstage",
    "stargazers_count": 30710,
    "open_issues_count": 452,
    "forks_count": 6641
  },
  {
    "full_name": "temporalio/awesome-temporal",
    "stargazers_count": 249,
    "open_issues_count": 0,
    "forks_count": 19
  },
  {
    "full_name": "temporalio/cli",
    "stargazers_count": 297,
    "open_issues_count": 74,
    "forks_count": 50
  },
  {
    "full_name": "pR0Ps/slack-to-discord",
    "stargazers_count": 91,
    "open_issues_count": 8,
    "forks_count": 16
  },
  {
    "full_name": "home-assistant/core",
    "stargazers_count": 80090,
    "open_issues_count": 3104,
    "forks_count": 34279
  },
  {
    "full_name": "openedx/frontend-platform",
    "stargazers_count": 35,
    "open_issues_count": 40,
    "forks_count": 73
  },
  {
    "full_name": "cgzirim/seek-tune",
    "stargazers_count": 4768,
    "open_issues_count": 5,
    "forks_count": 522
  },
  {
    "full_name": "spuder/OpenSpool",
    "stargazers_count": 518,
    "open_issues_count": 42,
    "forks_count": 27
  },
  {
    "full_name": "MichiganTypeScript/typescript-types-only-wasm-runtime",
    "stargazers_count": 2304,
    "open_issues_count": 6,
    "forks_count": 33
  },
  {
    "full_name": "AdguardTeam/AdGuardHome",
    "stargazers_count": 29135,
    "open_issues_count": 1154,
    "forks_count": 2065
  },
  {
    "full_name": "Turtlecute33/toolz",
    "stargazers_count": 163,
    "open_issues_count": 0,
    "forks_count": 18
  },
  {
    "full_name": "vitiko98/qobuz-dl",
    "stargazers_count": 1708,
    "open_issues_count": 138,
    "forks_count": 223
  },
  {
    "full_name": "QobuzDL/Qobuz-DL",
    "stargazers_count": 322,
    "open_issues_count": 17,
    "forks_count": 34
  },
  {
    "full_name": "JemPH/QobuzDL-Browser",
    "stargazers_count": 48,
    "open_issues_count": 0,
    "forks_count": 5
  }
]