[
  {
    "full_name": "gkjohnson/three-bvh-csg",
    "stargazers_count": 142,
    "open_issues_count": 34,
    "forks_count": 12
  },
  {
    "full_name": "andrelandgraf/all-things-web",
    "stargazers_count": 6,
    "open_issues_count": 0,
    "forks_count": 0
  },
  {
    "full_name": "honzaap/GithubCity",
    "stargazers_count": 859,
    "open_issues_count": 1,
    "forks_count": 38
  },
  {
    "full_name": "yt-dlp/yt-dlp",
    "stargazers_count": 31888,
    "open_issues_count": 756,
    "forks_count": 2526
  },
  {
    "full_name": "AykutSarac/jsoncrack.com",
    "stargazers_count": 11346,
    "open_issues_count": 31,
    "forks_count": 501
  },
  {
    "full_name": "facebook/react",
    "stargazers_count": 194639,
    "open_issues_count": 1096,
    "forks_count": 40219
  },
  {
    "full_name": "nibble-4bits/codewars-solutions-scraper",
    "stargazers_count": 3,
    "open_issues_count": 2,
    "forks_count": 2
  },
  {
    "full_name": "oslabs-beta/BACE",
    "stargazers_count": 83,
    "open_issues_count": 5,
    "forks_count": 4
  },
  {
    "full_name": "pyxelr/my-anki-decks-of-flashcards",
    "stargazers_count": 23,
    "open_issues_count": 0,
    "forks_count": 2
  },
  {
    "full_name": "lklima/rn-flight-animation",
    "stargazers_count": 190,
    "open_issues_count": 0,
    "forks_count": 18
  },
  {
    "full_name": "rwaldron/idiomatic.js",
    "stargazers_count": 20899,
    "open_issues_count": 53,
    "forks_count": 3006
  },
  {
    "full_name": "octoshrimpy/learn",
    "stargazers_count": 33,
    "open_issues_count": 12,
    "forks_count": 8
  },
  {
    "full_name": "isonmad/discord.js",
    "stargazers_count": 3,
    "open_issues_count": 0,
    "forks_count": 0
  },
  {
    "full_name": "discordjs/discord.js",
    "stargazers_count": 20818,
    "open_issues_count": 100,
    "forks_count": 3533
  },
  {
    "full_name": "uetchy/namae",
    "stargazers_count": 567,
    "open_issues_count": 8,
    "forks_count": 26
  },
  {
    "full_name": "tidyverse/dplyr",
    "stargazers_count": 4195,
    "open_issues_count": 34,
    "forks_count": 1457
  },
  {
    "full_name": "airbnb/css",
    "stargazers_count": 6498,
    "open_issues_count": 21,
    "forks_count": 1403
  },
  {
    "full_name": "leon-ai/leon",
    "stargazers_count": 10902,
    "open_issues_count": 64,
    "forks_count": 855
  },
  {
    "full_name": "Rob--W/dont-track-me-google",
    "stargazers_count": 305,
    "open_issues_count": 8,
    "forks_count": 20
  },
  {
    "full_name": "30-seconds/30-seconds-of-code",
    "stargazers_count": 102736,
    "open_issues_count": 0,
    "forks_count": 10694
  },
  {
    "full_name": "freeCodeCamp/demo-projects",
    "stargazers_count": 73,
    "open_issues_count": 4,
    "forks_count": 34
  },
  {
    "full_name": "getify/You-Dont-Know-JS",
    "stargazers_count": 158949,
    "open_issues_count": 131,
    "forks_count": 31136
  },
  {
    "full_name": "ossu/computer-science",
    "stargazers_count": 123678,
    "open_issues_count": 10,
    "forks_count": 16483
  },
  {
    "full_name": "EbookFoundation/free-programming-books",
    "stargazers_count": 248176,
    "open_issues_count": 45,
    "forks_count": 50627
  },
  {
    "full_name": "sindresorhus/awesome",
    "stargazers_count": 219130,
    "open_issues_count": 43,
    "forks_count": 24184
  },
  {
    "full_name": "sass/sass",
    "stargazers_count": 14142,
    "open_issues_count": 101,
    "forks_count": 2007
  },
  {
    "full_name": "BenRoe/awesome-mechanical-keyboard",
    "stargazers_count": 2198,
    "open_issues_count": 13,
    "forks_count": 173
  },
  {
    "full_name": "hankchizljaw/modern-css-reset",
    "stargazers_count": 2608,
    "open_issues_count": 17,
    "forks_count": 438
  },
  {
    "full_name": "denysdovhan/wtfjs",
    "stargazers_count": 28250,
    "open_issues_count": 22,
    "forks_count": 2037
  },
  {
    "full_name": "metagrover/ES6-for-humans",
    "stargazers_count": 5957,
    "open_issues_count": 1,
    "forks_count": 457
  }
]